reahl/messages/reahl-web
reahl/messages/af/LC_MESSAGES/reahl-web.mo
reahl/messages/af/LC_MESSAGES/reahl-web.po
reahl/web/__init__.py
reahl/web/csrf.py
reahl/web/dhtml.py
reahl/web/egg.py
reahl/web/fw.py
reahl/web/interfaces.py
reahl/web/layout.py
reahl/web/libraries.py
reahl/web/plotly.py
reahl/web/ui.py
reahl/web/bootstrap/__init__.py
reahl/web/bootstrap/carousel.py
reahl/web/bootstrap/files.py
reahl/web/bootstrap/forms.py
reahl/web/bootstrap/grid.py
reahl/web/bootstrap/navbar.py
reahl/web/bootstrap/navs.py
reahl/web/bootstrap/page.py
reahl/web/bootstrap/pagination.py
reahl/web/bootstrap/popups.py
reahl/web/bootstrap/reahl.bootstrapcueinput.js
reahl/web/bootstrap/reahl.bootstrapfileuploadli.js
reahl/web/bootstrap/reahl.bootstrapfileuploadpanel.js
reahl/web/bootstrap/reahl.bootstrapform.js
reahl/web/bootstrap/reahl.bootstrappopupa.js
reahl/web/bootstrap/reahl.carousel.css
reahl/web/bootstrap/reahl.datatable.css
reahl/web/bootstrap/reahl.files.css
reahl/web/bootstrap/reahl.files.js
reahl/web/bootstrap/reahl.pagination.js
reahl/web/bootstrap/tabbedpanel.py
reahl/web/bootstrap/tables.py
reahl/web/bootstrap/ui.py
reahl/web/holder/__init__.py
reahl/web/holder/holder-2.9.9.js
reahl/web/holder/holder-2.9.9.min.js
reahl/web/holder/holder.py
reahl/web/static/IE9.js
reahl/web/static/__init__.py
reahl/web/static/html5shiv-printshiv-3.7.3.js
reahl/web/static/plotly-2.29.0.min.js
reahl/web/static/reahl.ajaxlink.js
reahl/web/static/reahl.csrf.js
reahl/web/static/reahl.css
reahl/web/static/reahl.form.js
reahl/web/static/reahl.hashchange.js
reahl/web/static/reahl.modaldialog.js
reahl/web/static/reahl.plotlychart.js
reahl/web/static/reahl.primitiveinput.js
reahl/web/static/reahl.runningonbadge.css
reahl/web/static/reahl.textinput.js
reahl/web/static/reahl.validate.js
reahl/web/static/runningon.png
reahl/web/static/underscore-umd-min.1.13.6.js
reahl/web/static/bootstrap-4.6.2/css/bootstrap-grid.css
reahl/web/static/bootstrap-4.6.2/css/bootstrap-grid.css.map
reahl_web-7.0.3.dist-info/COPYING
reahl_web-7.0.3.dist-info/LICENSE
reahl_web-7.0.3.dist-info/METADATA
reahl_web-7.0.3.dist-info/WHEEL
reahl_web-7.0.3.dist-info/entry_points.txt
reahl_web-7.0.3.dist-info/reahl-component.toml
reahl_web-7.0.3.dist-info/top_level.txt
reahl_web-7.0.3.dist-info/RECORD
